s1282006_learn/__init__.py
s1282006_learn/statistics/__init__.py
s1282006_learn/statistics/frequenciesOfItems.py
s1282006_learn/visualization/__init__.py
s1282006_learn/visualization/heatMapItemsFrequencies.py
s1282006_learn-2023.7.31.dist-info/METADATA
s1282006_learn-2023.7.31.dist-info/WHEEL
s1282006_learn-2023.7.31.dist-info/top_level.txt
s1282006_learn-2023.7.31.dist-info/RECORD
